Metadata-Version: 2.1
Name: api-client-jsonmarshal
Version: 0.0.1
Summary: API Client extension for automatic request marshalling.
Home-page: https://github.com/MikeWooster/api-client-jsonmarshal
Author: Mike Wooster
Author-email: 
License: UNKNOWN
Platform: UNKNOWN
Classifier: Development Status :: 5 - Production/Stable
Classifier: Programming Language :: Python :: 3.8
Classifier: License :: OSI Approved :: MIT License
Classifier: Operating System :: OS Independent
Classifier: Intended Audience :: Developers
Requires-Python: >=3.7
Provides-Extra: production
Provides-Extra: test
Provides-Extra: lint
Provides-Extra: docs
Provides-Extra: dev
Provides-Extra: deploy
